supermag_api/__init__.py
supermag_api/supermag_api.py
supermag_api-0.0.6.dist-info/licenses/LICENSE
supermag_api-0.0.6.dist-info/METADATA
supermag_api-0.0.6.dist-info/WHEEL
supermag_api-0.0.6.dist-info/top_level.txt
supermag_api-0.0.6.dist-info/RECORD
