Metadata-Version: 2.4
Name: supermag_api
Version: 0.0.6
Summary: Python software to fetch SuperMag data
Author-email: Sandy Antunes <sandy.antunes@jhuapl.edu>
License: BSD 3-Clause
Project-URL: Homepage, https://github.com/elwinter/supermag_api
Keywords: SUPERMAG
Classifier: Programming Language :: Python :: 3
Classifier: Operating System :: OS Independent
Requires-Python: >=3.8
License-File: LICENSE
Requires-Dist: certifi
Requires-Dist: pandas
Dynamic: license-file
